business/__init__.py
business/calendar.py
business/py.typed
business_python-2.1.0.dist-info/LICENSE
business_python-2.1.0.dist-info/METADATA
business_python-2.1.0.dist-info/WHEEL
business_python-2.1.0.dist-info/RECORD
