Metadata-Version: 2.1
Name: business-python
Version: 2.1.0
Summary: Date calculations based on business calendars.
Home-page: https://github.com/gocardless/business-python
Keywords: business days,working days,calendar,date
Author: GoCardless
Author-email: engineering@gocardless.com
Requires-Python: >=3.8.1,<4.0.0
Classifier: Development Status :: 5 - Production/Stable
Classifier: License :: OSI Approved :: MIT License
Classifier: Operating System :: OS Independent
Classifier: Programming Language :: Python :: 3
Classifier: Programming Language :: Python :: 3.9
Classifier: Programming Language :: Python :: 3.10
Classifier: Programming Language :: Python :: 3.11
Classifier: Programming Language :: Python :: 3.10
Classifier: Programming Language :: Python :: 3.11
Classifier: Programming Language :: Python :: 3.8
Classifier: Programming Language :: Python :: 3.9
Classifier: Topic :: Office/Business :: Scheduling
Classifier: Topic :: Software Development :: Libraries :: Python Modules
Requires-Dist: python-dateutil (>=2.8.2,<3.0.0)
Requires-Dist: pyyaml (>=6.0.1,<7.0.0)
Project-URL: Bug Tracker, https://github.com/gocardless/business-python/issues
Project-URL: Changelog, https://github.com/gocardless/business-python/blob/master/CHANGELOG.md
Project-URL: Repository, https://github.com/gocardless/business-python
Project-URL: Security, https://github.com/gocardless/business-python/blob/master/SECURITY.md
